exponent/__init__.py
exponent/cli.py
exponent/py.typed
exponent/commands/cloud_commands.py
exponent/commands/common.py
exponent/commands/config_commands.py
exponent/commands/github_app_commands.py
exponent/commands/listen_commands.py
exponent/commands/run_commands.py
exponent/commands/settings.py
exponent/commands/shell_commands.py
exponent/commands/theme.py
exponent/commands/types.py
exponent/commands/upgrade.py
exponent/commands/utils.py
exponent/core/config.py
exponent/core/graphql/__init__.py
exponent/core/graphql/client.py
exponent/core/graphql/cloud_config_queries.py
exponent/core/graphql/get_chats_query.py
exponent/core/graphql/github_config_queries.py
exponent/core/graphql/mutations.py
exponent/core/graphql/queries.py
exponent/core/graphql/subscriptions.py
exponent/core/remote_execution/checkpoints.py
exponent/core/remote_execution/cli_rpc_types.py
exponent/core/remote_execution/client.py
exponent/core/remote_execution/code_execution.py
exponent/core/remote_execution/command_execution.py
exponent/core/remote_execution/error_info.py
exponent/core/remote_execution/exceptions.py
exponent/core/remote_execution/file_write.py
exponent/core/remote_execution/files.py
exponent/core/remote_execution/git.py
exponent/core/remote_execution/session.py
exponent/core/remote_execution/system_context.py
exponent/core/remote_execution/tool_execution.py
exponent/core/remote_execution/truncation.py
exponent/core/remote_execution/types.py
exponent/core/remote_execution/utils.py
exponent/core/remote_execution/languages/python_execution.py
exponent/core/remote_execution/languages/shell_streaming.py
exponent/core/remote_execution/languages/types.py
exponent/core/types/__init__.py
exponent/core/types/command_data.py
exponent/core/types/event_types.py
exponent/core/types/generated/__init__.py
exponent/core/types/generated/strategy_info.py
exponent/migration-docs/login.md
exponent/utils/__init__.py
exponent/utils/colors.py
exponent/utils/version.py
indent_ai-0.0.7.dist-info/METADATA
indent_ai-0.0.7.dist-info/WHEEL
indent_ai-0.0.7.dist-info/entry_points.txt
indent_ai-0.0.7.dist-info/RECORD
