Metadata-Version: 2.4
Name: indent-ai
Version: 0.0.7
Summary: Indent is an AI Pair Programmer
Author-email: Sashank Thupukari <sashank@exponent.run>
Requires-Python: <3.13,>=3.10
Requires-Dist: anyio<5,>=4.6.0
Requires-Dist: async-timeout<5,>=4.0.3; python_version < '3.11'
Requires-Dist: beautifulsoup4[chardet]<5,>=4.13.4
Requires-Dist: certifi<2025,>=2024.8.30
Requires-Dist: click<9,>=8.1.7
Requires-Dist: colour<0.2,>=0.1.5
Requires-Dist: diff-match-patch<20230431,>=20230430
Requires-Dist: eval-type-backport<0.3,>=0.2.0
Requires-Dist: gevent==24.2.1
Requires-Dist: git-python>=1.0.3
Requires-Dist: gitignore-parser<0.2,>=0.1.11
Requires-Dist: gql[httpx,websockets]<4,>=3.5.0
Requires-Dist: httpx<0.28,>=0.27.0
Requires-Dist: ipykernel<7,>=6.29.4
Requires-Dist: jupyter-client<9,>=8.6.1
Requires-Dist: msgspec>=0.19.0
Requires-Dist: packaging~=24.1
Requires-Dist: pip<26,>=25.0.1
Requires-Dist: prompt-toolkit<4,>=3.0.36
Requires-Dist: pydantic-settings<3,>=2.2.1
Requires-Dist: pydantic[email]<3,>=2.6.4
Requires-Dist: pygit2<2,>=1.15.0
Requires-Dist: python-ripgrep==0.0.8
Requires-Dist: pyyaml>=6.0.2
Requires-Dist: questionary<3,>=2.0.1
Requires-Dist: rapidfuzz<4,>=3.9.0
Requires-Dist: rich<14,>=13.7.1
Requires-Dist: sentry-sdk<3,>=2.1.1
Requires-Dist: toml<0.11,>=0.10.2
Requires-Dist: websockets~=11.0
